LICENSE.txt
MANIFEST.in
README.md
setup.py
offtracker/X_offplot.py
offtracker/X_offtracker.py
offtracker/X_sequence.py
offtracker/__init__.py
offtracker/_version.py
offtracker.egg-info/PKG-INFO
offtracker.egg-info/SOURCES.txt
offtracker.egg-info/dependency_links.txt
offtracker.egg-info/requires.txt
offtracker.egg-info/top_level.txt
offtracker/snakefile/Snakefile_QC.smk
offtracker/snakefile/Snakefile_offtracker.smk
offtracker/utility/1.1_bed2fr.py
offtracker/utility/1.3_bdg_normalize_v4.0.py
offtracker/utility/bedGraphToBigWig
offtracker/utility/hg38.chrom.sizes
offtracker/utility/mm10.chrom.sizes
offtracker/utility/offtracker_blacklist_hg38.merged.bed
offtracker/utility/offtracker_blacklist_mm10.merged.bed
scripts/offtracker_analysis.py
scripts/offtracker_candidates.py
scripts/offtracker_config.py
scripts/offtracker_correction.py
scripts/offtracker_init.py
scripts/offtracker_plot.py
scripts/offtracker_qc.py