Metadata-Version: 2.1
Name: offtracker
Version: 2.13.2
Summary: Tracking-seq data analysis
Home-page: https://github.com/Lan-lab/offtracker
Author: Runda Xu
Author-email: xrd18@tsinghua.org.cn
Requires-Python: >=3.6.0
License-File: LICENSE.txt
